{
  "d62fa2b41e961c2c": [
    {
      "graph_id_type": "md_id",
      "proprietary_id": "mp-1047596",
      "datasource": "MP",
      "url": "https://next-gen.materialsproject.org/materials/mp-1047596",
      "filehash": "a2459d8d6cbd78c6"
    }
  ],
  "d62f6cddad03c6ea": [
    {
      "graph_id_type": "md_id",
      "proprietary_id": "mp-775264",
      "datasource": "MP",
      "url": "https://next-gen.materialsproject.org/materials/mp-775264",
      "filehash": "44502011e9c2e933"
    }
  ],
  "d62fce03d37574b6": [
    {
      "graph_id_type": "topo_md_id",
      "proprietary_id": "mp-541689",
      "datasource": "MP",
      "url": "https://next-gen.materialsproject.org/materials/mp-541689",
      "filehash": "63fd78cb94649cc9"
    }
  ],
  "d62ff8dea5cfe847": [
    {
      "graph_id_type": "md_id",
      "proprietary_id": "mp-15919",
      "datasource": "MP",
      "url": "https://next-gen.materialsproject.org/materials/mp-15919",
      "filehash": "5962ffe9adced52f"
    }
  ]
}