{
  "40058ef5f79ae44f": [
    {
      "graph_id_type": "dc_id",
      "proprietary_id": "mp-1201140",
      "datasource": "MP",
      "url": "https://next-gen.materialsproject.org/materials/mp-1201140",
      "filehash": "bd369874fb292b9f"
    }
  ],
  "4005718b2639102e": [
    {
      "graph_id_type": "topo_md_id",
      "proprietary_id": "mp-758479",
      "datasource": "MP",
      "url": "https://next-gen.materialsproject.org/materials/mp-758479",
      "filehash": "30d7b22947b059f5"
    },
    {
      "graph_id_type": "topo_md_id",
      "proprietary_id": "mp-19462",
      "datasource": "MP",
      "url": "https://next-gen.materialsproject.org/materials/mp-19462",
      "filehash": "be37864117334e57"
    }
  ],
  "4005a9ff8c8a3f9c": [
    {
      "graph_id_type": "md_id",
      "proprietary_id": "mp-1372141",
      "datasource": "MP",
      "url": "https://next-gen.materialsproject.org/materials/mp-1372141",
      "filehash": "3f8504cbf8d281e6"
    }
  ],
  "4005972d844dcb32": [
    {
      "graph_id_type": "topo_md_id",
      "proprietary_id": "mp-761098",
      "datasource": "MP",
      "url": "https://next-gen.materialsproject.org/materials/mp-761098",
      "filehash": "2d438b6900ccfaa0"
    }
  ]
}