{
  "414b3eab9590a680": [
    {
      "graph_id_type": "topo_md_id",
      "proprietary_id": "mp-555845",
      "datasource": "MP",
      "url": "https://next-gen.materialsproject.org/materials/mp-555845",
      "filehash": "b06b9f9a5caf9bc9"
    }
  ],
  "414bd3ddf5a24118": [
    {
      "graph_id_type": "topo_md_id",
      "proprietary_id": "mp-1338483",
      "datasource": "MP",
      "url": "https://next-gen.materialsproject.org/materials/mp-1338483",
      "filehash": "35f9fbfdf97417c1"
    }
  ],
  "414b1ca8182fb4dd": [
    {
      "graph_id_type": "topo_md_id",
      "proprietary_id": "mp-1317719",
      "datasource": "MP",
      "url": "https://next-gen.materialsproject.org/materials/mp-1317719",
      "filehash": "25e5e12bd0cfc2b6"
    }
  ],
  "414b687d90609baa": [
    {
      "graph_id_type": "dc_id",
      "proprietary_id": "mp-1113283",
      "datasource": "MP",
      "url": "https://next-gen.materialsproject.org/materials/mp-1113283",
      "filehash": "e1fc08d429c8a57d"
    }
  ],
  "414b71b64faaef3e": [
    {
      "graph_id_type": "md_id",
      "proprietary_id": "mp-555411",
      "datasource": "MP",
      "url": "https://next-gen.materialsproject.org/materials/mp-555411",
      "filehash": "1c5620fe7cb41be3"
    }
  ],
  "414bbcac0c392166": [
    {
      "graph_id_type": "md_id",
      "proprietary_id": "mp-1018902",
      "datasource": "MP",
      "url": "https://next-gen.materialsproject.org/materials/mp-1018902",
      "filehash": "c6fdc6ac5ebc1173"
    }
  ],
  "414bdfc4b82836ef": [
    {
      "graph_id_type": "dc_id",
      "proprietary_id": "mp-1001602",
      "datasource": "MP",
      "url": "https://next-gen.materialsproject.org/materials/mp-1001602",
      "filehash": "463f8a7aa97e281d"
    }
  ]
}