{
  "4e2f205b1cddc352": [
    {
      "graph_id_type": "dc_id",
      "proprietary_id": "mp-861572",
      "datasource": "MP",
      "url": "https://next-gen.materialsproject.org/materials/mp-861572",
      "filehash": "3e33ece0459aaf62"
    }
  ],
  "4e2f2856dbcc94d9": [
    {
      "graph_id_type": "dc_id",
      "proprietary_id": "mp-1208132",
      "datasource": "MP",
      "url": "https://next-gen.materialsproject.org/materials/mp-1208132",
      "filehash": "c7ec2a3bfad2f4e9"
    }
  ],
  "4e2ff254b7c9ca72": [
    {
      "graph_id_type": "topo_md_id",
      "proprietary_id": "mp-756521",
      "datasource": "MP",
      "url": "https://next-gen.materialsproject.org/materials/mp-756521",
      "filehash": "8f9db084a7c12567"
    }
  ],
  "4e2f343de6bb132e": [
    {
      "graph_id_type": "topo_md_id",
      "proprietary_id": "mp-1174806",
      "datasource": "MP",
      "url": "https://next-gen.materialsproject.org/materials/mp-1174806",
      "filehash": "15393d9816ab6fc8"
    }
  ],
  "4e2f835aebe05c48": [
    {
      "graph_id_type": "dc_id",
      "proprietary_id": "mp-1227699",
      "datasource": "MP",
      "url": "https://next-gen.materialsproject.org/materials/mp-1227699",
      "filehash": "712efbcecde9ea4d"
    }
  ],
  "4e2f9d6a2f177579": [
    {
      "graph_id_type": "topo_md_id",
      "proprietary_id": "mp-654299",
      "datasource": "MP",
      "url": "https://next-gen.materialsproject.org/materials/mp-654299",
      "filehash": "7fc010de7fa0d119"
    },
    {
      "graph_id_type": "topo_md_id",
      "proprietary_id": "mp-621927",
      "datasource": "MP",
      "url": "https://next-gen.materialsproject.org/materials/mp-621927",
      "filehash": "52d3a20b102549b3"
    }
  ],
  "4e2f8f99b5f8f1a8": [
    {
      "graph_id_type": "md_id",
      "proprietary_id": "mp-1201747",
      "datasource": "MP",
      "url": "https://next-gen.materialsproject.org/materials/mp-1201747",
      "filehash": "3560a7e7d0005348"
    }
  ],
  "4e2ffbb598657b4e": [
    {
      "graph_id_type": "dc_id",
      "proprietary_id": "mp-1198140",
      "datasource": "MP",
      "url": "https://next-gen.materialsproject.org/materials/mp-1198140",
      "filehash": "6f0ccaf57e105b1e"
    }
  ]
}