{
  "78fde63adc7fbeaa": [
    {
      "graph_id_type": "md_id",
      "proprietary_id": "mp-776509",
      "datasource": "MP",
      "url": "https://next-gen.materialsproject.org/materials/mp-776509",
      "filehash": "98d91843491ca304"
    }
  ],
  "78fdd1d249ef678a": [
    {
      "graph_id_type": "md_id",
      "proprietary_id": "mp-556363",
      "datasource": "MP",
      "url": "https://next-gen.materialsproject.org/materials/mp-556363",
      "filehash": "26e0122bbc1ed738"
    }
  ],
  "78fd62b823adde0a": [
    {
      "graph_id_type": "md_id",
      "proprietary_id": "mp-1247927",
      "datasource": "MP",
      "url": "https://next-gen.materialsproject.org/materials/mp-1247927",
      "filehash": "8059beeaf614e5be"
    }
  ]
}