{
  "72f5e8dbed1936e5": [
    {
      "graph_id_type": "topo_md_id",
      "proprietary_id": "mp-2218742",
      "datasource": "MP",
      "url": "https://next-gen.materialsproject.org/materials/mp-2218742",
      "filehash": "cbfdf4f1143fb7bf"
    }
  ],
  "72f517316824a296": [
    {
      "graph_id_type": "dc_id",
      "proprietary_id": "mp-640563",
      "datasource": "MP",
      "url": "https://next-gen.materialsproject.org/materials/mp-640563",
      "filehash": "0ade2fafc4dd343c"
    }
  ],
  "72f5c8c72aa47dab": [
    {
      "graph_id_type": "dc_id",
      "proprietary_id": "mp-20095",
      "datasource": "MP",
      "url": "https://next-gen.materialsproject.org/materials/mp-20095",
      "filehash": "09317ae9428ec96d"
    }
  ],
  "72f508cf6c24dd46": [
    {
      "graph_id_type": "md_id",
      "proprietary_id": "mp-1210843",
      "datasource": "MP",
      "url": "https://next-gen.materialsproject.org/materials/mp-1210843",
      "filehash": "d6859afe2c529cd1"
    }
  ]
}