{
  "f30d536c49eb9318": [
    {
      "graph_id_type": "md_id",
      "proprietary_id": "mp-1339646",
      "datasource": "MP",
      "url": "https://next-gen.materialsproject.org/materials/mp-1339646",
      "filehash": "6b23bb6748de91ad"
    }
  ],
  "f30d1f1e2539299a": [
    {
      "graph_id_type": "md_id",
      "proprietary_id": "mp-1214038",
      "datasource": "MP",
      "url": "https://next-gen.materialsproject.org/materials/mp-1214038",
      "filehash": "f993dee316286afa"
    }
  ],
  "f30d6c9b0b6d5317": [
    {
      "graph_id_type": "dc_id",
      "proprietary_id": "mp-4276",
      "datasource": "MP",
      "url": "https://next-gen.materialsproject.org/materials/mp-4276",
      "filehash": "6416ebf93bd6d10c"
    }
  ],
  "f30d206a5bb2e353": [
    {
      "graph_id_type": "md_id",
      "proprietary_id": "mp-1183497",
      "datasource": "MP",
      "url": "https://next-gen.materialsproject.org/materials/mp-1183497",
      "filehash": "752bac4f5fb0e300"
    }
  ],
  "f30df97e3e1beaeb": [
    {
      "graph_id_type": "md_id",
      "proprietary_id": "mp-705035",
      "datasource": "MP",
      "url": "https://next-gen.materialsproject.org/materials/mp-705035",
      "filehash": "349323946325686f"
    }
  ],
  "f30d2b6d6fcf4cba": [
    {
      "graph_id_type": "dc_id",
      "proprietary_id": "mp-1229031",
      "datasource": "MP",
      "url": "https://next-gen.materialsproject.org/materials/mp-1229031",
      "filehash": "abeeeeecf68353db"
    }
  ],
  "f30d821c500b031a": [
    {
      "graph_id_type": "md_id",
      "proprietary_id": "mp-1179197",
      "datasource": "MP",
      "url": "https://next-gen.materialsproject.org/materials/mp-1179197",
      "filehash": "c769351f6a9dcca8"
    }
  ],
  "f30d516630972816": [
    {
      "graph_id_type": "dc_id",
      "proprietary_id": "mp-754159",
      "datasource": "MP",
      "url": "https://next-gen.materialsproject.org/materials/mp-754159",
      "filehash": "a11ba6b1add2d55b"
    }
  ]
}