{
  "9de5aa86d48f9a5a": [
    {
      "graph_id_type": "md_id",
      "proprietary_id": "mp-1018151",
      "datasource": "MP",
      "url": "https://next-gen.materialsproject.org/materials/mp-1018151",
      "filehash": "a1af784dac69a5af"
    }
  ],
  "9de5a99219b580e7": [
    {
      "graph_id_type": "md_id",
      "proprietary_id": "mp-4975",
      "datasource": "MP",
      "url": "https://next-gen.materialsproject.org/materials/mp-4975",
      "filehash": "b330f18cb1e3b825"
    }
  ],
  "9de53a6e766bab53": [
    {
      "graph_id_type": "md_id",
      "proprietary_id": "mp-2714040",
      "datasource": "MP",
      "url": "https://next-gen.materialsproject.org/materials/mp-2714040",
      "filehash": "52f24091d3c25210"
    }
  ],
  "9de531205bdcc5b4": [
    {
      "graph_id_type": "md_id",
      "proprietary_id": "mp-771822",
      "datasource": "MP",
      "url": "https://next-gen.materialsproject.org/materials/mp-771822",
      "filehash": "f0d92fb4a577fd9f"
    }
  ],
  "9de53f5592bddb50": [
    {
      "graph_id_type": "md_id",
      "proprietary_id": "mp-1101351",
      "datasource": "MP",
      "url": "https://next-gen.materialsproject.org/materials/mp-1101351",
      "filehash": "7563271d3c36f267"
    }
  ],
  "9de5af59606c1c38": [
    {
      "graph_id_type": "md_id",
      "proprietary_id": "mp-1235533",
      "datasource": "MP",
      "url": "https://next-gen.materialsproject.org/materials/mp-1235533",
      "filehash": "a9fc74d0a788c4fa"
    }
  ],
  "9de5cacd087a1257": [
    {
      "graph_id_type": "md_id",
      "proprietary_id": "mp-1018071",
      "datasource": "MP",
      "url": "https://next-gen.materialsproject.org/materials/mp-1018071",
      "filehash": "64af190518ef1e03"
    }
  ]
}