{
  "195fe3bdc833e4b3": [
    {
      "graph_id_type": "topo_md_id",
      "proprietary_id": "mp-1228656",
      "datasource": "MP",
      "url": "https://next-gen.materialsproject.org/materials/mp-1228656",
      "filehash": "bfafab79d109f392"
    }
  ],
  "195f6e612f4772fe": [
    {
      "graph_id_type": "dc_id",
      "proprietary_id": "mp-1043124",
      "datasource": "MP",
      "url": "https://next-gen.materialsproject.org/materials/mp-1043124",
      "filehash": "8dcfb0cf8facb126"
    }
  ],
  "195fa0a1da642223": [
    {
      "graph_id_type": "topo_md_id",
      "proprietary_id": "mp-761072",
      "datasource": "MP",
      "url": "https://next-gen.materialsproject.org/materials/mp-761072",
      "filehash": "04b6f4109bee180d"
    }
  ],
  "195ff2d2be29617d": [
    {
      "graph_id_type": "dc_id",
      "proprietary_id": "mp-797419",
      "datasource": "MP",
      "url": "https://next-gen.materialsproject.org/materials/mp-797419",
      "filehash": "f20aa2e78c33504b"
    }
  ],
  "195fd6c2c341f749": [
    {
      "graph_id_type": "md_id",
      "proprietary_id": "mp-1313407",
      "datasource": "MP",
      "url": "https://next-gen.materialsproject.org/materials/mp-1313407",
      "filehash": "e6ecb104068d82d8"
    }
  ]
}