{
  "091c9c3459d4f894": [
    {
      "graph_id_type": "md_id",
      "proprietary_id": "mp-1184656",
      "datasource": "MP",
      "url": "https://next-gen.materialsproject.org/materials/mp-1184656",
      "filehash": "8bfff1a173ad766a"
    }
  ],
  "091c3d459be8ce9f": [
    {
      "graph_id_type": "dc_id",
      "proprietary_id": "mp-1209244",
      "datasource": "MP",
      "url": "https://next-gen.materialsproject.org/materials/mp-1209244",
      "filehash": "b19506baa21abb62"
    }
  ],
  "091cd149c2b5ae2c": [
    {
      "graph_id_type": "md_id",
      "proprietary_id": "mp-2229590",
      "datasource": "MP",
      "url": "https://next-gen.materialsproject.org/materials/mp-2229590",
      "filehash": "0785a53b8219dd28"
    }
  ],
  "091c0d8d4ee56666": [
    {
      "graph_id_type": "dc_id",
      "proprietary_id": "mp-1196808",
      "datasource": "MP",
      "url": "https://next-gen.materialsproject.org/materials/mp-1196808",
      "filehash": "31adf3063b4dd8c3"
    }
  ],
  "091cad55df306f79": [
    {
      "graph_id_type": "dc_id",
      "proprietary_id": "mp-1064244",
      "datasource": "MP",
      "url": "https://next-gen.materialsproject.org/materials/mp-1064244",
      "filehash": "0841f10bbda545b9"
    }
  ]
}