{
  "0c908cbb1512a242": [
    {
      "graph_id_type": "dc_id",
      "proprietary_id": "mp-1199251",
      "datasource": "MP",
      "url": "https://next-gen.materialsproject.org/materials/mp-1199251",
      "filehash": "69c759ac8313f7ac"
    }
  ],
  "0c909a5c32ee6fcd": [
    {
      "graph_id_type": "dc_id",
      "proprietary_id": "mp-756283",
      "datasource": "MP",
      "url": "https://next-gen.materialsproject.org/materials/mp-756283",
      "filehash": "20527ee57aaf1750"
    }
  ],
  "0c9042a1882c1aa2": [
    {
      "graph_id_type": "dc_id",
      "proprietary_id": "mp-1197576",
      "datasource": "MP",
      "url": "https://next-gen.materialsproject.org/materials/mp-1197576",
      "filehash": "448cde5e1bcb75d7"
    }
  ],
  "0c900612f95965bd": [
    {
      "graph_id_type": "md_id",
      "proprietary_id": "mp-1579563",
      "datasource": "MP",
      "url": "https://next-gen.materialsproject.org/materials/mp-1579563",
      "filehash": "e03c48cdd983338d"
    }
  ]
}