{
  "0b15c8d85d5ca616": [
    {
      "graph_id_type": "dc_id",
      "proprietary_id": "mp-1185203",
      "datasource": "MP",
      "url": "https://next-gen.materialsproject.org/materials/mp-1185203",
      "filehash": "1db1003f5948f89e"
    }
  ],
  "0b159d6644a52f8d": [
    {
      "graph_id_type": "dc_id",
      "proprietary_id": "mp-1072856",
      "datasource": "MP",
      "url": "https://next-gen.materialsproject.org/materials/mp-1072856",
      "filehash": "8a4f2c219a71c5d3"
    }
  ],
  "0b15618f66e31eed": [
    {
      "graph_id_type": "dc_id",
      "proprietary_id": "mp-1029948",
      "datasource": "MP",
      "url": "https://next-gen.materialsproject.org/materials/mp-1029948",
      "filehash": "932186ecd6f1939b"
    }
  ],
  "0b158b73b1de6c20": [
    {
      "graph_id_type": "md_id",
      "proprietary_id": "mp-778088",
      "datasource": "MP",
      "url": "https://next-gen.materialsproject.org/materials/mp-778088",
      "filehash": "125c955672476890"
    }
  ],
  "0b155ade1be5fd10": [
    {
      "graph_id_type": "topo_md_id",
      "proprietary_id": "mp-1178891",
      "datasource": "MP",
      "url": "https://next-gen.materialsproject.org/materials/mp-1178891",
      "filehash": "35fe2980446675b4"
    }
  ]
}