{
  "48edfd397e6421d9": [
    {
      "graph_id_type": "md_id",
      "proprietary_id": "mp-1213248",
      "datasource": "MP",
      "url": "https://next-gen.materialsproject.org/materials/mp-1213248",
      "filehash": "275d1c9daa46458f"
    }
  ],
  "48ed9bbc61819cff": [
    {
      "graph_id_type": "dc_id",
      "proprietary_id": "mp-1206965",
      "datasource": "MP",
      "url": "https://next-gen.materialsproject.org/materials/mp-1206965",
      "filehash": "474ffa66c7189bfe"
    }
  ],
  "48edd3ad2b12cd23": [
    {
      "graph_id_type": "md_id",
      "proprietary_id": "mp-2227518",
      "datasource": "MP",
      "url": "https://next-gen.materialsproject.org/materials/mp-2227518",
      "filehash": "a4542c40a5d01a13"
    }
  ],
  "48edd361df6df383": [
    {
      "graph_id_type": "dc_id",
      "proprietary_id": "mp-1096434",
      "datasource": "MP",
      "url": "https://next-gen.materialsproject.org/materials/mp-1096434",
      "filehash": "bf69f034afcffaad"
    }
  ],
  "48ed704ff39c5453": [
    {
      "graph_id_type": "md_id",
      "proprietary_id": "mp-1186185",
      "datasource": "MP",
      "url": "https://next-gen.materialsproject.org/materials/mp-1186185",
      "filehash": "fefdbb2a3bcc144d"
    }
  ],
  "48ed3e7bdeb1932c": [
    {
      "graph_id_type": "md_id",
      "proprietary_id": "mp-14401",
      "datasource": "MP",
      "url": "https://next-gen.materialsproject.org/materials/mp-14401",
      "filehash": "8afebe8b4866e910"
    }
  ],
  "48ed886ab11f779b": [
    {
      "graph_id_type": "dc_id",
      "proprietary_id": "mp-758159",
      "datasource": "MP",
      "url": "https://next-gen.materialsproject.org/materials/mp-758159",
      "filehash": "91e866345bddc6b1"
    }
  ]
}