{
  "59fcad85d5cfc248": [
    {
      "graph_id_type": "topo_md_id",
      "proprietary_id": "mp-1202361",
      "datasource": "MP",
      "url": "https://next-gen.materialsproject.org/materials/mp-1202361",
      "filehash": "963eea87812133fc"
    },
    {
      "graph_id_type": "topo_md_id",
      "proprietary_id": "mp-1213325",
      "datasource": "MP",
      "url": "https://next-gen.materialsproject.org/materials/mp-1213325",
      "filehash": "4f70b26670c67fe0"
    },
    {
      "graph_id_type": "topo_md_id",
      "proprietary_id": "mp-1179542",
      "datasource": "MP",
      "url": "https://next-gen.materialsproject.org/materials/mp-1179542",
      "filehash": "547ca015ff9404fa"
    },
    {
      "graph_id_type": "topo_md_id",
      "proprietary_id": "mp-560911",
      "datasource": "MP",
      "url": "https://next-gen.materialsproject.org/materials/mp-560911",
      "filehash": "66ca16a095ba45e3"
    },
    {
      "graph_id_type": "topo_md_id",
      "proprietary_id": "mp-1207531",
      "datasource": "MP",
      "url": "https://next-gen.materialsproject.org/materials/mp-1207531",
      "filehash": "80f9a80d1f899907"
    },
    {
      "graph_id_type": "topo_md_id",
      "proprietary_id": "mp-556656",
      "datasource": "MP",
      "url": "https://next-gen.materialsproject.org/materials/mp-556656",
      "filehash": "fa0cf44fceafd28f"
    },
    {
      "graph_id_type": "topo_md_id",
      "proprietary_id": "mp-23566",
      "datasource": "MP",
      "url": "https://next-gen.materialsproject.org/materials/mp-23566",
      "filehash": "81ce64ab06f38673"
    },
    {
      "graph_id_type": "topo_md_id",
      "proprietary_id": "mp-554323",
      "datasource": "MP",
      "url": "https://next-gen.materialsproject.org/materials/mp-554323",
      "filehash": "dfd69697a1b99945"
    },
    {
      "graph_id_type": "topo_md_id",
      "proprietary_id": "mp-556141",
      "datasource": "MP",
      "url": "https://next-gen.materialsproject.org/materials/mp-556141",
      "filehash": "856ad70576f377a8"
    },
    {
      "graph_id_type": "topo_md_id",
      "proprietary_id": "mp-561135",
      "datasource": "MP",
      "url": "https://next-gen.materialsproject.org/materials/mp-561135",
      "filehash": "df31eb68cd59571c"
    },
    {
      "graph_id_type": "topo_md_id",
      "proprietary_id": "mp-23087",
      "datasource": "MP",
      "url": "https://next-gen.materialsproject.org/materials/mp-23087",
      "filehash": "841d7b90f2e4efad"
    },
    {
      "graph_id_type": "topo_md_id",
      "proprietary_id": "mp-562349",
      "datasource": "MP",
      "url": "https://next-gen.materialsproject.org/materials/mp-562349",
      "filehash": "ff01f91de8dd26ec"
    }
  ],
  "59fc648f760d055b": [
    {
      "graph_id_type": "topo_md_id",
      "proprietary_id": "mp-1204007",
      "datasource": "MP",
      "url": "https://next-gen.materialsproject.org/materials/mp-1204007",
      "filehash": "93579b0b3aead023"
    }
  ],
  "59fc1b5a1787725d": [
    {
      "graph_id_type": "md_id",
      "proprietary_id": "mp-1218017",
      "datasource": "MP",
      "url": "https://next-gen.materialsproject.org/materials/mp-1218017",
      "filehash": "77e69d46af4aba20"
    },
    {
      "graph_id_type": "md_id",
      "proprietary_id": "mp-1545240",
      "datasource": "MP",
      "url": "https://next-gen.materialsproject.org/materials/mp-1545240",
      "filehash": "4d2d75c9c6756c0f"
    }
  ],
  "59fc41024008ece0": [
    {
      "graph_id_type": "topo_md_id",
      "proprietary_id": "mp-1190470",
      "datasource": "MP",
      "url": "https://next-gen.materialsproject.org/materials/mp-1190470",
      "filehash": "abb0f00477694aa4"
    },
    {
      "graph_id_type": "topo_md_id",
      "proprietary_id": "mp-1190452",
      "datasource": "MP",
      "url": "https://next-gen.materialsproject.org/materials/mp-1190452",
      "filehash": "0da7cba21705f8c9"
    },
    {
      "graph_id_type": "topo_md_id",
      "proprietary_id": "mp-1190341",
      "datasource": "MP",
      "url": "https://next-gen.materialsproject.org/materials/mp-1190341",
      "filehash": "01627ab278920193"
    },
    {
      "graph_id_type": "topo_md_id",
      "proprietary_id": "mp-1190385",
      "datasource": "MP",
      "url": "https://next-gen.materialsproject.org/materials/mp-1190385",
      "filehash": "76110dc4f0723ea8"
    }
  ],
  "59fcd993ab55cae9": [
    {
      "graph_id_type": "topo_md_id",
      "proprietary_id": "mp-1177930",
      "datasource": "MP",
      "url": "https://next-gen.materialsproject.org/materials/mp-1177930",
      "filehash": "5a9f0bf0d841ca38"
    }
  ],
  "59fc6807e6cd7d1e": [
    {
      "graph_id_type": "topo_md_id",
      "proprietary_id": "mp-1103126",
      "datasource": "MP",
      "url": "https://next-gen.materialsproject.org/materials/mp-1103126",
      "filehash": "c9d168ad2cb5d64e"
    },
    {
      "graph_id_type": "topo_md_id",
      "proprietary_id": "mp-724678",
      "datasource": "MP",
      "url": "https://next-gen.materialsproject.org/materials/mp-724678",
      "filehash": "2616c0937cad6ad7"
    }
  ],
  "59fc59c1f90bba63": [
    {
      "graph_id_type": "dc_id",
      "proprietary_id": "mp-9858",
      "datasource": "MP",
      "url": "https://next-gen.materialsproject.org/materials/mp-9858",
      "filehash": "dfdcc17c510ef83a"
    }
  ],
  "59fc5a30525f8d01": [
    {
      "graph_id_type": "dc_id",
      "proprietary_id": "mp-1072880",
      "datasource": "MP",
      "url": "https://next-gen.materialsproject.org/materials/mp-1072880",
      "filehash": "23e2102d8e10a8f0"
    }
  ],
  "59fc0d6c640f7d34": [
    {
      "graph_id_type": "md_id",
      "proprietary_id": "mp-667198",
      "datasource": "MP",
      "url": "https://next-gen.materialsproject.org/materials/mp-667198",
      "filehash": "230dd461cb68184e"
    }
  ]
}