{
  "76cc5b8a3f3e56b9": [
    {
      "graph_id_type": "dc_id",
      "proprietary_id": "mp-1204079",
      "datasource": "MP",
      "url": "https://next-gen.materialsproject.org/materials/mp-1204079",
      "filehash": "b8d45f7f98f252a0"
    }
  ],
  "76cc71a8bae272d9": [
    {
      "graph_id_type": "topo_md_id",
      "proprietary_id": "mp-1220483",
      "datasource": "MP",
      "url": "https://next-gen.materialsproject.org/materials/mp-1220483",
      "filehash": "049ea6c18aca1a89"
    },
    {
      "graph_id_type": "topo_md_id",
      "proprietary_id": "mp-1220598",
      "datasource": "MP",
      "url": "https://next-gen.materialsproject.org/materials/mp-1220598",
      "filehash": "9d447c27c5d8e727"
    }
  ],
  "76cc1557d6d6a1e6": [
    {
      "graph_id_type": "md_id",
      "proprietary_id": "mp-759837",
      "datasource": "MP",
      "url": "https://next-gen.materialsproject.org/materials/mp-759837",
      "filehash": "9ef9df4651df8516"
    }
  ],
  "76cc8488424a373b": [
    {
      "graph_id_type": "topo_md_id",
      "proprietary_id": "mp-757932",
      "datasource": "MP",
      "url": "https://next-gen.materialsproject.org/materials/mp-757932",
      "filehash": "a65597c039ea6919"
    }
  ],
  "76ccb273c6cee86c": [
    {
      "graph_id_type": "md_id",
      "proprietary_id": "mp-30938",
      "datasource": "MP",
      "url": "https://next-gen.materialsproject.org/materials/mp-30938",
      "filehash": "50b92d8268fed9ec"
    }
  ]
}