[
    {
        "accuracy": 0.9759,
        "batch": 8,
        "dropout": 0.2983508631636968,
        "duration": 135876914173,
        "lr": 0.060477515701433886,
        "momentum": 0.010845907293562496,
        "transform": "norm_512_flip",
        "uid": "f5583ddddbad81bc7e249245c95a3cc3"
    },
    {
        "accuracy": 0.9734,
        "batch": 1,
        "dropout": 0.21592838956096327,
        "duration": 226405458375,
        "lr": 0.10519411174169459,
        "momentum": 0.12435603176910692,
        "transform": "norm_128_flip",
        "uid": "09d5cf2cebb6c757a0dcff9703b27375"
    },
    {
        "accuracy": 0.9379,
        "batch": 64,
        "dropout": 0.11607203643601549,
        "duration": 195954025810,
        "lr": 0.025132165425614316,
        "momentum": 0.6081274042642831,
        "transform": "norm_512_flip",
        "uid": "6c489f0b8f3c181f0cb9ae061e22c4ab"
    }
]