{
  "3491d20e7485ddef": [
    {
      "graph_id_type": "topo_md_id",
      "proprietary_id": "mp-1102943",
      "datasource": "MP",
      "url": "https://next-gen.materialsproject.org/materials/mp-1102943",
      "filehash": "c3cbdbf72ded0853"
    },
    {
      "graph_id_type": "topo_md_id",
      "proprietary_id": "mp-13541",
      "datasource": "MP",
      "url": "https://next-gen.materialsproject.org/materials/mp-13541",
      "filehash": "671ecfa125d515e1"
    },
    {
      "graph_id_type": "topo_md_id",
      "proprietary_id": "mp-549737",
      "datasource": "MP",
      "url": "https://next-gen.materialsproject.org/materials/mp-549737",
      "filehash": "87277e3f102bd91c"
    }
  ],
  "349120585e993e1c": [
    {
      "graph_id_type": "dc_id",
      "proprietary_id": "mp-1101092",
      "datasource": "MP",
      "url": "https://next-gen.materialsproject.org/materials/mp-1101092",
      "filehash": "25d2774708386a3d"
    }
  ],
  "34917e1712780650": [
    {
      "graph_id_type": "md_id",
      "proprietary_id": "mp-759170",
      "datasource": "MP",
      "url": "https://next-gen.materialsproject.org/materials/mp-759170",
      "filehash": "2d1a1341e56108b3"
    }
  ],
  "349130519d6fc178": [
    {
      "graph_id_type": "md_id",
      "proprietary_id": "mp-1009491",
      "datasource": "MP",
      "url": "https://next-gen.materialsproject.org/materials/mp-1009491",
      "filehash": "22ce28d98b7c28fa"
    }
  ],
  "3491da63876f4bc5": [
    {
      "graph_id_type": "topo_md_id",
      "proprietary_id": "mp-554225",
      "datasource": "MP",
      "url": "https://next-gen.materialsproject.org/materials/mp-554225",
      "filehash": "a2c92033489a4c41"
    },
    {
      "graph_id_type": "topo_md_id",
      "proprietary_id": "mp-504524",
      "datasource": "MP",
      "url": "https://next-gen.materialsproject.org/materials/mp-504524",
      "filehash": "6180cb9f0dbd25e1"
    }
  ],
  "34915fa807afd4eb": [
    {
      "graph_id_type": "dc_id",
      "proprietary_id": "mp-771147",
      "datasource": "MP",
      "url": "https://next-gen.materialsproject.org/materials/mp-771147",
      "filehash": "049bd726184e856f"
    }
  ]
}